README.rst
setup.cfg
setup.py
multiblock/__init__.py
multiblock/_version.py
multiblock/command.py
multiblock.egg-info/PKG-INFO
multiblock.egg-info/SOURCES.txt
multiblock.egg-info/dependency_links.txt
multiblock.egg-info/entry_points.txt
multiblock.egg-info/requires.txt
multiblock.egg-info/top_level.txt