Metadata-Version: 2.1
Name: multiblock
Version: 0.0.1
Summary: Sync block and mute lists over multiple Mastodon accounts
Home-page: https://github.com/moggers87/multiblock
Author: Matt Molyneaux
Author-email: moggers87+git@moggers87.co.uk
License: GPLv3
Download-URL: https://pypi.org/project/multiblock/
Platform: UNKNOWN
Classifier: Development Status :: 3 - Alpha
Classifier: Intended Audience :: Developers
Classifier: License :: OSI Approved :: GNU General Public License v3 or later (GPLv3+)
Classifier: Programming Language :: Python :: 3
Classifier: Programming Language :: Python :: 3.5
Classifier: Programming Language :: Python :: 3.6
Classifier: Programming Language :: Python :: 3.7
Classifier: Programming Language :: Python :: 3.8
Provides-Extra: docs
